aioes/__init__.py
aioes/connection.py
aioes/exception.py
aioes/log.py
aioes/pool.py
aioes/transport.py
aioes/client/__init__.py
aioes/client/cat.py
aioes/client/cluster.py
aioes/client/indices.py
aioes/client/nodes.py
aioes/client/snapshot.py
aioes/client/utils.py
aioes-0.7.2.dist-info/DESCRIPTION.rst
aioes-0.7.2.dist-info/METADATA
aioes-0.7.2.dist-info/RECORD
aioes-0.7.2.dist-info/WHEEL
aioes-0.7.2.dist-info/metadata.json
aioes-0.7.2.dist-info/top_level.txt
